Workbook
Name ExpenseCategories: Lists!$A$2:$A$22
Name PaymentMethods: Lists!$C$2:$C$8

Sheet Expense Log
A1: EXPENSE TRACKING LOG
A2: Record every purchase the day it happens. File the receipt, then tick it off here.
A4: Month: | D4: Project:
A6: Date | B6: Category | C6: Vendor | D6: Description | E6: Payment Method | F6: Amount | G6: Running Total
G7: =IF(F7="","",SUM($F$7:F7))
G8: =IF(F8="","",SUM($F$7:F8))
G9: =IF(F9="","",SUM($F$7:F9))
G10: =IF(F10="","",SUM($F$7:F10))
G11: =IF(F11="","",SUM($F$7:F11))
G12: =IF(F12="","",SUM($F$7:F12))
G13: =IF(F13="","",SUM($F$7:F13))
G14: =IF(F14="","",SUM($F$7:F14))
G15: =IF(F15="","",SUM($F$7:F15))
G16: =IF(F16="","",SUM($F$7:F16))
G17: =IF(F17="","",SUM($F$7:F17))
G18: =IF(F18="","",SUM($F$7:F18))
... G66: =IF(F66="","",SUM($F$7:F66))
A67: TOTAL THIS SHEET | F67: =SUM(F7:F66)
A69: © 2026 Build Your House · build-your-house.com

Sheet Lists
A1: Budget Category | C1: Payment Method | E1: Edit these lists to change the dropdown choices on the Expense Log sheet.
A2: Land & Site Costs | C2: Cash
A3: Site Preparation | C3: Check
A4: Foundation | C4: Debit Card
A5: Framing | C5: Credit Card
A6: Roofing | C6: ACH / Transfer
A7: Exterior (Siding, Windows, Doors) | C7: Draw / Construction Loan
A8: Rough-In (Plumbing, Electrical, HVAC) | C8: Owner Financing
A9: Insulation
A10: Drywall
A11: Doors & Interior Trim
A12: Flooring
A13: Cabinets & Countertops
A14: Fixtures (Plumbing, Lighting)
A15: Paint & Finishes
A16: Appliances
A17: Landscaping
A18: Permits & Fees
A19: Tools & Equipment
A20: Labor (Subcontractors)
... A22: Other

Sheet Category Summary
A1: CATEGORY SUMMARY
A2: Budgeted amounts are yours to enter; spend is pulled from the Expense Log automatically.
A4: Budget Category | B4: Budgeted | C4: Spent (from log) | D4: Remaining
A5: Land & Site Costs | C5: =SUMIF('Expense Log'!$B$7:$B$66,$A5,'Expense Log'!$F$7:$F$66) | D5: =IF(B5="","",B5-C5)
A6: Site Preparation | C6: =SUMIF('Expense Log'!$B$7:$B$66,$A6,'Expense Log'!$F$7:$F$66) | D6: =IF(B6="","",B6-C6)
A7: Foundation | C7: =SUMIF('Expense Log'!$B$7:$B$66,$A7,'Expense Log'!$F$7:$F$66) | D7: =IF(B7="","",B7-C7)
A8: Framing | C8: =SUMIF('Expense Log'!$B$7:$B$66,$A8,'Expense Log'!$F$7:$F$66) | D8: =IF(B8="","",B8-C8)
A9: Roofing | C9: =SUMIF('Expense Log'!$B$7:$B$66,$A9,'Expense Log'!$F$7:$F$66) | D9: =IF(B9="","",B9-C9)
A10: Exterior (Siding, Windows, Doors) | C10: =SUMIF('Expense Log'!$B$7:$B$66,$A10,'Expense Log'!$F$7:$F$66) | D10: =IF(B10="","",B10-C10)
A11: Rough-In (Plumbing, Electrical, HVAC) | C11: =SUMIF('Expense Log'!$B$7:$B$66,$A11,'Expense Log'!$F$7:$F$66) | D11: =IF(B11="","",B11-C11)
A12: Insulation | C12: =SUMIF('Expense Log'!$B$7:$B$66,$A12,'Expense Log'!$F$7:$F$66) | D12: =IF(B12="","",B12-C12)
A13: Drywall | C13: =SUMIF('Expense Log'!$B$7:$B$66,$A13,'Expense Log'!$F$7:$F$66) | D13: =IF(B13="","",B13-C13)
A14: Doors & Interior Trim | C14: =SUMIF('Expense Log'!$B$7:$B$66,$A14,'Expense Log'!$F$7:$F$66) | D14: =IF(B14="","",B14-C14)
A15: Flooring | C15: =SUMIF('Expense Log'!$B$7:$B$66,$A15,'Expense Log'!$F$7:$F$66) | D15: =IF(B15="","",B15-C15)
A16: Cabinets & Countertops | C16: =SUMIF('Expense Log'!$B$7:$B$66,$A16,'Expense Log'!$F$7:$F$66) | D16: =IF(B16="","",B16-C16)
... A25: Other | C25: =SUMIF('Expense Log'!$B$7:$B$66,$A25,'Expense Log'!$F$7:$F$66) | D25: =IF(B25="","",B25-C25)
A26: TOTAL | B26: =SUM(B5:B25) | C26: =SUM(C5:C25) | D26: =SUM(D5:D25)
A28: © 2026 Build Your House · build-your-house.com
